Workbook
Name Accountrecivableturn: ComparisionSheet!$G$16
Name CurrentRatio: ComparisionSheet!$G$10
Name debtnetworthratio: ComparisionSheet!$G$12
Name Debtratio: ComparisionSheet!$G$13
Name ROA: ComparisionSheet!$G$2

Sheet Data
A1: Bankrupt? | B1: ROA(A) before interest and % after tax | C1: Operating Gross Margin | D1: Operating Profit Rate | E1: Cash flow rate | F1: Cash Flow Per Share | G1: Revenue Per Share (Yuan Â¥) | H1: Total Asset Growth Rate | I1: Net Value Growth Rate | J1: Current Ratio | K1: Quick Ratio | L1: Total debt/Total net worth | M1: Debt ratio % | N1: Net worth/Assets | O1: Total Asset Turnover | P1: Accounts Receivable Turnover | Q1: Inventory Turnover Rate (times) | R1: Working Capital to Total Assets | S1: Cash/Total Assets | T1: Net Income to Total Assets | U1: Interest Coverage Ratio (Interest expense to EBIT) | V1: Risk Flag
A2: 1 | B2: 0.42438945 | C2: 0.60145721 | D2: 0.9989692 | E2: 0.45814314 | F2: 0.31166443 | G2: 0.01755978 | H2: 4980000000 | I2: 0.00032697727 | J2: 0.0022589633 | K2: 0.0012077551 | L2: 0.021265924 | M2: 0.20757626 | N2: 0.79242374 | O2: 0.086956522 | P2: 0.0018138841 | Q2: 0.0001820926 | R2: 0.67277529 | S2: 0.004094406 | T2: 0.71684534 | U2: 0.56405011 | V2: =IF(AND(data[[#This Row],[ Debt ratio %]]>Debtratio,data[[#This Row],[ Current Ratio]]<CurrentRatio,data[[#This Row],[ Total debt/Total net worth]]>debtnetworthratio),"High Risk","Low Risk") -> High Risk
A3: 1 | B3: 0.53821413 | C3: 0.61023509 | D3: 0.99894598 | E3: 0.46186726 | F3: 0.3181368 | G3: 0.021144335 | H3: 6110000000 | I3: 0.0004430401 | J3: 0.0060162059 | K3: 0.0040393668 | L3: 0.012502394 | M3: 0.17117635 | N3: 0.82882365 | O3: 0.064467766 | P3: 0.0012863563 | Q3: 9360000000 | R3: 0.75111092 | S3: 0.014947727 | T3: 0.79529714 | U3: 0.57017495 | V3: =IF(AND(data[[#This Row],[ Debt ratio %]]>Debtratio,data[[#This Row],[ Current Ratio]]<CurrentRatio,data[[#This Row],[ Total debt/Total net worth]]>debtnetworthratio),"High Risk","Low Risk") -> High Risk
A4: 1 | B4: 0.49901875 | C4: 0.60145001 | D4: 0.99885735 | E4: 0.45852059 | F4: 0.30710193 | G4: 0.0059440083 | H4: 7280000000 | I4: 0.00039642531 | J4: 0.011542554 | K4: 0.0053475602 | L4: 0.021247686 | M4: 0.2075158 | N4: 0.7924842 | O4: 0.014992504 | P4: 0.0014953385 | Q4: 65000000 | R4: 0.82950191 | S4: 0.00099094445 | T4: 0.7746697 | U4: 0.56370608 | V4: =IF(AND(data[[#This Row],[ Debt ratio %]]>Debtratio,data[[#This Row],[ Current Ratio]]<CurrentRatio,data[[#This Row],[ Total debt/Total net worth]]>debtnetworthratio),"High Risk","Low Risk") -> Low Risk
A5: 1 | B5: 0.45126472 | C5: 0.58354113 | D5: 0.99869975 | E5: 0.46570544 | F5: 0.32167362 | G5: 0.014368468 | H5: 4880000000 | I5: 0.00038242591 | J5: 0.0041940587 | K5: 0.0028964911 | L5: 0.0095724017 | M5: 0.15146476 | N5: 0.84853524 | O5: 0.089955022 | P5: 0.0019660556 | Q5: 7130000000 | R5: 0.72575418 | S5: 0.018850625 | T5: 0.73955453 | U5: 0.56466342 | V5: =IF(AND(data[[#This Row],[ Debt ratio %]]>Debtratio,data[[#This Row],[ Current Ratio]]<CurrentRatio,data[[#This Row],[ Total debt/Total net worth]]>debtnetworthratio),"High Risk","Low Risk") -> Low Risk
A6: 1 | B6: 0.53843218 | C6: 0.59878349 | D6: 0.99897313 | E6: 0.46274628 | F6: 0.31916248 | G6: 0.029689792 | H6: 5510000000 | I6: 0.00043894758 | J6: 0.0060224461 | K6: 0.0037274466 | L6: 0.0051496001 | M6: 0.10650905 | N6: 0.89349095 | O6: 0.17541229 | P6: 0.0014486726 | Q6: 0.00016336744 | R6: 0.75182245 | S6: 0.014160974 | T6: 0.79501587 | U6: 0.57561665 | V6: =IF(AND(data[[#This Row],[ Debt ratio %]]>Debtratio,data[[#This Row],[ Current Ratio]]<CurrentRatio,data[[#This Row],[ Total debt/Total net worth]]>debtnetworthratio),"High Risk","Low Risk") -> Low Risk
A7: 1 | B7: 0.41517662 | C7: 0.59017138 | D7: 0.9987581 | E7: 0.46586145 | F7: 0.32538728 | G7: 0.01810427 | H7: 608000000 | I7: 0.00035178193 | J7: 0.0027400851 | K7: 0.0008546614 | L7: 0.014213152 | M7: 0.18042749 | N7: 0.81957251 | O7: 0.095952024 | P7: 0.0015278017 | Q7: 650000000 | R7: 0.68672865 | S7: 0.0026452256 | T7: 0.7104205 | U7: 0.56453834 | V7: =IF(AND(data[[#This Row],[ Debt ratio %]]>Debtratio,data[[#This Row],[ Current Ratio]]<CurrentRatio,data[[#This Row],[ Total debt/Total net worth]]>debtnetworthratio),"High Risk","Low Risk") -> High Risk
A8: 0 | B8: 0.44570432 | C8: 0.61994984 | D8: 0.99899312 | E8: 0.46102011 | F8: 0.31668671 | G8: 0.030914893 | H8: 5720000000 | I8: 0.00035175697 | J8: 0.0046720603 | K8: 0.0028690422 | L8: 0.024441222 | M8: 0.21610182 | N8: 0.78389818 | O8: 0.10044978 | P8: 0.0016617126 | Q8: 0.00016202993 | R8: 0.72941646 | S8: 0.022988598 | T8: 0.7366191 | U8: 0.56420012 | V8: =IF(AND(data[[#This Row],[ Debt ratio %]]>Debtratio,data[[#This Row],[ Current Ratio]]<CurrentRatio,data[[#This Row],[ Total debt/Total net worth]]>debtnetworthratio),"High Risk","Low Risk") -> High Risk
A9: 0 | B9: 0.57092237 | C9: 0.60173828 | D9: 0.99900895 | E9: 0.46702398 | F9: 0.32411403 | G9: 0.042560915 | H9: 6630000000 | I9: 0.00045105046 | J9: 0.0096573802 | K9: 0.0073045477 | L9: 0.0052781805 | M9: 0.10820207 | N9: 0.89179793 | O9: 0.21889055 | P9: 0.0013350512 | Q9: 0.0001990981 | R9: 0.79700521 | S9: 0.014615913 | T9: 0.81535039 | U9: 0.56608894 | V9: =IF(AND(data[[#This Row],[ Debt ratio %]]>Debtratio,data[[#This Row],[ Current Ratio]]<CurrentRatio,data[[#This Row],[ Total debt/Total net worth]]>debtnetworthratio),"High Risk","Low Risk") -> Low Risk
A10: 0 | B10: 0.54513737 | C10: 0.60361204 | D10: 0.99896077 | E10: 0.46314218 | F10: 0.31877343 | G10: 0.026604353 | H10: 6890000000 | I10: 0.0004527224 | J10: 0.013498866 | K10: 0.011823024 | L10: 0.0022661159 | M10: 0.058590561 | N10: 0.94140944 | O10: 0.15442279 | P10: 0.0013025879 | Q10: 0.00030418826 | R10: 0.81373752 | S10: 0.14518922 | T10: 0.80364729 | U10: 0.5655919 | V10: =IF(AND(data[[#This Row],[ Debt ratio %]]>Debtratio,data[[#This Row],[ Current Ratio]]<CurrentRatio,data[[#This Row],[ Total debt/Total net worth]]>debtnetworthratio),"High Risk","Low Risk") -> Low Risk
A11: 0 | B11: 0.55091583 | C11: 0.59920869 | D11: 0.99900063 | E11: 0.47057531 | F11: 0.33016199 | G11: 0.078663581 | H11: 5550000000 | I11: 0.00044491168 | J11: 0.011474535 | K11: 0.0075166534 | L11: 0.0063542436 | M11: 0.12129274 | N11: 0.87870726 | O11: 0.34782609 | P11: 0.0014689621 | Q11: 0.00020597673 | R11: 0.82569587 | S11: 0.0087727909 | T11: 0.80419466 | U11: 0.56666762 | V11: =IF(AND(data[[#This Row],[ Debt ratio %]]>Debtratio,data[[#This Row],[ Current Ratio]]<CurrentRatio,data[[#This Row],[ Total debt/Total net worth]]>debtnetworthratio),"High Risk","Low Risk") -> Low Risk
A12: 0 | B12: 0.56754252 | C12: 0.61402586 | D12: 0.99897845 | E12: 0.46481803 | F12: 0.31916248 | G12: 0.01553307 | H12: 747000000 | I12: 0.00044855502 | J12: 0.0060973289 | K12: 0.0034492138 | L12: 0.0049325637 | M12: 0.1035765 | N12: 0.8964235 | O12: 0.076461769 | P12: 0.0019396792 | Q12: 0.00015629774 | R12: 0.75120434 | S12: 0.0020568362 | T12: 0.81411061 | U12: 0.56589153 | V12: =IF(AND(data[[#This Row],[ Debt ratio %]]>Debtratio,data[[#This Row],[ Current Ratio]]<CurrentRatio,data[[#This Row],[ Total debt/Total net worth]]>debtnetworthratio),"High Risk","Low Risk") -> Low Risk
A13: 0 | B13: 0.54971653 | C13: 0.62371179 | D13: 0.99897533 | E13: 0.46549072 | F13: 0.31986985 | G13: 0.011419151 | H13: 5730000000 | I13: 0.00045506811 | J13: 0.0086289902 | K13: 0.0051229777 | L13: 0.0042923973 | M13: 0.094385827 | N13: 0.90561417 | O13: 0.062968516 | P13: 0.00080752336 | Q13: 655000000 | R13: 0.76911389 | S13: 0.020542229 | T13: 0.80488695 | U13: 0.56698265 | V13: =IF(AND(data[[#This Row],[ Debt ratio %]]>Debtratio,data[[#This Row],[ Current Ratio]]<CurrentRatio,data[[#This Row],[ Total debt/Total net worth]]>debtnetworthratio),"High Risk","Low Risk") -> Low Risk
... A6820: 0 | B6820: 0.57010467 | C6820: 0.62740887 | D6820: 0.9980803 | E6820: 0.42772116 | F6820: 0.30579331 | G6820: 0.00066548694 | H6820: 9350000000 | I6820: 0.00051862692 | J6820: 0.051348358 | K6820: 0.040897108 | L6820: 0.00046143043 | M6820: 0.014148804 | N6820: 0.9858512 | O6820: 0.0029985007 | P6820: 0.00032463251 | Q6820: 19100000 | R6820: 0.87375937 | S6820: 0.23814705 | T6820: 0.81595588 | U6820: 0.56516694 | V6820: =IF(AND(data[[#This Row],[ Debt ratio %]]>Debtratio,data[[#This Row],[ Current Ratio]]<CurrentRatio,data[[#This Row],[ Total debt/Total net worth]]>debtnetworthratio),"High Risk","Low Risk") -> Low Risk

Sheet Model accuracy
D6: High risk flag when bankruptancy | E6: Low risk flag when bankcruptancy | G6: True flag of bankruptacny | J6: False flag of bankruptancy
D7: =COUNTIFS(Data!V:V,"High Risk",Data!A:A,1) -> 159 | E7: =COUNTIFS(Data!V:V,"Low Risk",Data!A:A,1) -> 61 | G7: =D7/(D7+E7) -> 0.72272727 | J7: =E7/(D7+E7) -> 0.27727273
D9: High risk flag when healthy state | E9: Low risk flag when healthy state | G9: True flag of healthy state | J9: False flag of healthy state
D10: =COUNTIFS(Data!V:V,"High Risk",Data!A:A,0) -> 1044 | E10: =COUNTIFS(Data!V:V,"Low Risk",Data!A:A,0) -> 5555 | G10: =E10/(D10+E10) -> 0.84179421 | J10: =D10/(D10+E10) -> 0.15820579

Sheet ComparisionSheet
A1: Indicators | B1: Median condition at bankruptancy | C1: Median value at healthy state | D1: Ratio | E1: Bankrupt effect high? | F1: Biggest differentatior | G1: Thresold indicator
A2: ROA(A) before interest and % after tax | B2: {=MEDIAN(IF(Data!$A2:$A6820=1,Data!B2:B6820))} -> 0.49021478 | C2: {=MEDIAN(IF(Data!$A$2:$A$6820=0,Data!B2:B6820))} -> 0.56121893 | D2: =B2/C2 -> 0.87348227 | E2: =IF(OR(D2>1,D2<0.8),TRUE,FALSE) -> FALSE | F2: =IF(E2,A2,"NOT AFFECT BANKRUPTANCY MUCH") -> NOT AFFECT BANKRUPTANCY MUCH | G2: =(B2+C2)/2 -> 0.52571686
A3: Operating Gross Margin | B3: =MEDIAN(IF(Data!$A2:$A6820=1,Data!C2:C6820)) -> 0.60599749 | C3: {=MEDIAN(IF(Data!$A$2:$A$6820=0,Data!C2:C6820))} -> 0.60623532 | D3: =B3/C3 -> 0.9996077 | E3: =IF(OR(D3>1,D3<0.8),TRUE,FALSE) -> FALSE | F3: =IF(E3,A3,"NOT AFFECT BANKRUPTANCY MUCH") -> NOT AFFECT BANKRUPTANCY MUCH | G3: =(B3+C3)/2 -> 0.6061164
A4: Operating Profit Rate | B4: {=MEDIAN(IF(Data!$A2:$A6820=1,Data!D2:D6820))} -> 0.99889895 | C4: {=MEDIAN(IF(Data!$A$2:$A$6820=0,Data!D2:D6820))} -> 0.99902478 | D4: =B4/C4 -> 0.99987405 | E4: =IF(OR(D4>1,D4<0.8),TRUE,FALSE) -> FALSE | F4: =IF(E4,A4,"NOT AFFECT BANKRUPTANCY MUCH") -> NOT AFFECT BANKRUPTANCY MUCH | G4: =(B4+C4)/2 -> 0.99896187
A5: Cash flow rate | B5: {=MEDIAN(IF(Data!$A2:$A6820=1,Data!E2:E6820))} -> 0.46126838 | C5: {=MEDIAN(IF(Data!$A$2:$A$6820=0,Data!E2:E6820))} -> 0.46530451 | D5: =B5/C5 -> 0.99132582 | E5: =IF(OR(D5>1,D5<0.8),TRUE,FALSE) -> FALSE | F5: =IF(E5,A5,"NOT AFFECT BANKRUPTANCY MUCH") -> NOT AFFECT BANKRUPTANCY MUCH | G5: =(B5+C5)/2 -> 0.46328645
A6: Cash Flow Per Share | B6: =MEDIAN(IF(Data!$A:$A=1,Data!F:F)) -> 0.32248709 | C6: {=MEDIAN(IF(Data!$A$2:$A$6820=0,Data!F2:F6820))} -> 0.32266393 | D6: =B6/C6 -> 0.99945193 | E6: =IF(OR(D6>1,D6<0.8),TRUE,FALSE) -> FALSE | F6: =IF(E6,A6,"NOT AFFECT BANKRUPTANCY MUCH") -> NOT AFFECT BANKRUPTANCY MUCH | G6: =(B6+C6)/2 -> 0.32257551
A7: Revenue Per Share (Yuan Â¥) | B7: {=MEDIAN(IF(Data!$A2:$A6820=1,Data!G2:G6820))} -> 0.018913441 | C7: {=MEDIAN(IF(Data!$A$2:$A$6820=0,Data!G2:G6820))} -> 0.027617708 | D7: =B7/C7 -> 0.68483023 | E7: =IF(OR(D7>1,D7<0.8),TRUE,FALSE) -> TRUE | F7: =IF(E7,A7,"NOT AFFECT BANKRUPTANCY MUCH") -> Revenue Per Share (Yuan Â¥) | G7: =(B7+C7)/2 -> 0.023265575
A8: Total Asset Growth Rate | B8: {=MEDIAN(IF(Data!$A2:$A6820=1,Data!H2:H6820))} -> 5420000000 | C8: {=MEDIAN(IF(Data!$A$2:$A$6820=0,Data!H2:H6820))} -> 6440000000 | D8: =B8/C8 -> 0.84161491 | E8: =IF(OR(D8>1,D8<0.8),TRUE,FALSE) -> FALSE | F8: =IF(E8,A8,"NOT AFFECT BANKRUPTANCY MUCH") -> NOT AFFECT BANKRUPTANCY MUCH | G8: =(B8+C8)/2 -> 5930000000
A9: Net Value Growth Rate | B9: {=MEDIAN(IF(Data!$A:$A=1,Data!I:I))} -> 0.00039571411 | C9: {=MEDIAN(IF(Data!$A$2:$A$6820=0,Data!I2:I6820))} -> 0.00046330306 | D9: =B9/C9 -> 0.85411505 | E9: =IF(OR(D9>1,D9<0.8),TRUE,FALSE) -> FALSE | F9: =IF(E9,A9,"NOT AFFECT BANKRUPTANCY MUCH") -> NOT AFFECT BANKRUPTANCY MUCH | G9: =(B9+C9)/2 -> 0.00042950859
A10: Current Ratio | B10: {=MEDIAN(IF(Data!$A:$A=1,Data!J:J))} -> 0.0060293104 | C10: {=MEDIAN(IF(Data!$D$2:$D$6820=0,Data!J2:J6820))} -> 0.014952215 | D10: =B10/C10 -> 0.4032386 | E10: =IF(OR(D10>1,D10<0.8),TRUE,FALSE) -> TRUE | F10: =IF(E10,A10,"NOT AFFECT BANKRUPTANCY MUCH") -> Current Ratio | G10: =(B10+C10)/2 -> 0.010490763
A11: Quick Ratio | B11: {=MEDIAN(IF(Data!$A:$A=1,Data!K:K))} -> 0.0027505125 | C11: {=MEDIAN(IF(Data!$A$2:$A$6820=0,Data!K2:K6820))} -> 0.0075790375 | D11: =B11/C11 -> 0.36291053 | E11: =IF(OR(D11>1,D11<0.8),TRUE,FALSE) -> TRUE | F11: =IF(E11,A11,"NOT AFFECT BANKRUPTANCY MUCH") -> Quick Ratio | G11: =(B11+C11)/2 -> 0.005164775
A12: Debt/Networth | B12: {=MEDIAN(IF(Data!$A:$A=1,Data!L:L))} -> 0.015723288 | C12: =MEDIAN(IF(Data!$A$2:$A$6820=0,Data!L2:L6820)) -> 0.0055462844 | D12: =B12/C12 -> 2.8349227 | E12: =IF(OR(D12>1,D12<0.8),TRUE,FALSE) -> TRUE | F12: =IF(E12,A12,"NOT AFFECT BANKRUPTANCY MUCH") -> Debt/Networth | G12: =(B12+C12)/2 -> 0.010634786
A13: Debt ratio % | B13: {=MEDIAN(IF(Data!$A:$A=1,Data!M:M))} -> 0.18742631 | C13: {=MEDIAN(IF(Data!$D$2:$D$6820=0,Data!M2:M6820))} -> 0.046406869 | D13: =B13/C13 -> 4.0387622 | E13: =IF(OR(D13>1,D13<0.8),TRUE,FALSE) -> TRUE | F13: =IF(E13,A13,"NOT AFFECT BANKRUPTANCY MUCH") -> Debt ratio % | G13: =(B13+C13)/2 -> 0.11691659
A14: Net worth/Assets | B14: {=MEDIAN(IF(Data!$A:$A=1,Data!N:N))} -> 0.81257369 | C14: =MEDIAN(IF(Data!$A$2:$A$6820=0,Data!N2:N6820)) -> 0.88859328 | D14: =B14/C14 -> 0.91444951 | E14: =IF(OR(D14>1,D14<0.8),TRUE,FALSE) -> FALSE | F14: =IF(E14,A14,"NOT AFFECT BANKRUPTANCY MUCH") -> NOT AFFECT BANKRUPTANCY MUCH | G14: =(B14+C14)/2 -> 0.85058349
A15: Total Asset Turnover | B15: {=MEDIAN(IF(Data!$A:$A=1,Data!O:O))} -> 0.083958021 | C15: {=MEDIAN(IF(Data!$A$2:$A$6820=0,Data!O2:O6820))} -> 0.11994003 | D15: =B15/C15 -> 0.7 | E15: =IF(OR(D15>1,D15<0.8),TRUE,FALSE) -> TRUE | F15: =IF(E15,A15,"NOT AFFECT BANKRUPTANCY MUCH") -> Total Asset Turnover | G15: =(B15+C15)/2 -> 0.10194903
A16: Accounts Receivable Turnover | B16: {=MEDIAN(IF(Data!$A:$A=1,Data!P:P))} -> 0.00094549217 | C16: {=MEDIAN(IF(Data!$D$2:$D$6820=0,Data!P2:P6820))} -> 0.0003855011 | D16: =B16/C16 -> 2.4526316 | E16: =IF(OR(D16>1,D16<0.8),TRUE,FALSE) -> TRUE | F16: =IF(E16,A16,"NOT AFFECT BANKRUPTANCY MUCH") -> Accounts Receivable Turnover | G16: =(B16+C16)/2 -> 0.00066549664
A17: Inventory Turnover Rate (times) | B17: {=AVERAGE(IF(Data!$A2:A6820=1,Data!Q2:Q6820))} -> 2.1246336e+09 | C17: =AVERAGE(IF(Data!$A$2:$A$6820=0,Data!Q2:Q6820)) -> 2.1491061e+09 | D17: =B17/C17 -> 0.98861274 | E17: =IF(OR(D17>1,D17<0.8),TRUE,FALSE) -> FALSE | F17: =IF(E17,A17,"NOT AFFECT BANKRUPTANCY MUCH") -> NOT AFFECT BANKRUPTANCY MUCH | G17: =(B17+C17)/2 -> 2.1368698e+09
A18: Working Capital to Total Assets | B18: {=MEDIAN(IF(Data!$A:$A=1,Data!R:R))} -> 0.75286658 | C18: {=MEDIAN(IF(Data!$A$2:$A$6820=0,Data!R2:R6820))} -> 0.81182208 | D18: =B18/C18 -> 0.92737879 | E18: =IF(OR(D18>1,D18<0.8),TRUE,FALSE) -> FALSE | F18: =IF(E18,A18,"NOT AFFECT BANKRUPTANCY MUCH") -> NOT AFFECT BANKRUPTANCY MUCH | G18: =(B18+C18)/2 -> 0.78234433
A19: Cash/Total Assets | B19: {=MEDIAN(IF(Data!$A:$A=1,Data!S:S))} -> 0.023754709 | C19: {=MEDIAN(IF(Data!$D$2:$D$6820=0,Data!S2:S6820))} -> 0.055439361 | D19: =B19/C19 -> 0.42848094 | E19: =IF(OR(D19>1,D19<0.8),TRUE,FALSE) -> TRUE | F19: =IF(E19,A19,"NOT AFFECT BANKRUPTANCY MUCH") -> Cash/Total Assets | G19: =(B19+C19)/2 -> 0.039597035
A20: Net Income to Total Assets | B20: {=MEDIAN(IF(Data!$A:$A=1,Data!T:T))} -> 0.76629694 | C20: {=MEDIAN(IF(Data!$A$2:$A$6820=0,Data!T2:T6820))} -> 0.81149184 | D20: =B20/C20 -> 0.9443064 | E20: =IF(OR(D20>1,D20<0.8),TRUE,FALSE) -> FALSE | F20: =IF(E20,A20,"NOT AFFECT BANKRUPTANCY MUCH") -> NOT AFFECT BANKRUPTANCY MUCH | G20: =(B20+C20)/2 -> 0.78889439
A21: Intrest coverage ratio | B21: {=MEDIAN(IF(Data!$A:$A=1,Data!U:U))} -> 0.56471167 | C21: {=MEDIAN(IF(Data!$A2:$A6024=0,Data!T2:T6024))} -> 0.81138482 | D21: =B21/C21 -> 0.695985 | E21: =IF(OR(D21>1,D21<0.8),TRUE,FALSE) -> TRUE | F21: =IF(E21,A21,"NOT AFFECT BANKRUPTANCY MUCH") -> Intrest coverage ratio | G21: =(B21+C21)/2 -> 0.68804824

Sheet Charts
F5: Bankrupt State vs Healthy State
