Workbook
Name AllAverage: 'Data Validation'!$C$13
Name AllbranchQuantiy: 'Data Validation'!$Q$8
Name AllBranchRevenue: 'Data Validation'!$M$10
Name AverageBRating: 'Branch B info'!$C$12
Name AverageCRating: 'BranchC info'!$H$15
Name AverageFilter: 'Data Validation'!$G$13
Name BranchAAverage: 'BranchA info'!$C$15
Name BranchAQuantity: 'BranchA info'!$O$14
Name BranchARevenue: 'BranchA info'!$L$13
Name BranchBQuantity: 'Branch B info'!$T$12
Name BranchBRevenue: 'Branch B info'!$Q$14
Name BranchCQuantity: 'BranchC info'!$E$15
Name BranchCRevenue: 'BranchC info'!$P$15
Name BranchQuantityFilter: 'Data Validation'!$Q$12
Name CustomerCount: 'Data Validation'!$D$6
Name CustomerCountA: 'BranchA info'!$Q$11
Name CustomerCountB: 'Branch B info'!$A$12
Name CustomerCountC: 'BranchC info'!$B$15
Name GrossProfitAllBranch: 'Data Validation'!$I$14
Name GrossProfitBranchA: 'BranchA info'!$A$15
Name GrossProfitBranchB: 'Branch B info'!$K$15
Name GrossProfitBranchC: 'BranchC info'!$K$17
Name GrossProfitFilter: 'Data Validation'!$L$14
Name InputBranch: 'Project Dashboard'!$F$10
Name InputCustomertyp: 'Project Dashboard'!$J$10
Name Inputgender: 'Project Dashboard'!$H$10
Name InputPayementMethod: 'Project Dashboard'!$L$10
Name LeasPurchasedB: ProductsnPayements!$G$10
Name LeastPurchasedAllbranch: ProductsnPayements!$R$10
Name LeastPurchasedBB: ProductsnPayements!$H$10
Name LeastPurchasedBC: ProductsnPayements!$M$10
Name LeastPurchasedC: ProductsnPayements!$L$10
Name LeastPurchasednumberALLB: ProductsnPayements!$S$10
Name LeastPurchasednumberBA: ProductsnPayements!$C$10
Name LeastPurchaseedA: ProductsnPayements!$B$10
Name LeastPurchaseFilter: 'Data Validation'!$R$15
Name LeastPurchaseFilterNumber: 'Data Validation'!$R$16
Name MostPayementAFilter: ProductsnPayements!$A$19
Name MostPayementAllBranchFilter: ProductsnPayements!$P$19
Name MostPayementAno: ProductsnPayements!$B$19
Name MostPayementBFilter: ProductsnPayements!$G$19
Name MostPayementBNo: ProductsnPayements!$H$19
Name MostPayementCfilter: ProductsnPayements!$L$19
Name MostPayementCNO: ProductsnPayements!$M$19
Name MostPayementNO: ProductsnPayements!$Q$19
Name MostpruchasedNumberBA: ProductsnPayements!$C$9
Name MostPurchasedA: ProductsnPayements!$B$9
Name MostPurchasedAllbranch: ProductsnPayements!$R$9
Name MostPurchasedB: ProductsnPayements!$G$9
Name MostPurchasedBB: ProductsnPayements!$H$9
Name MostPurchasedBC: ProductsnPayements!$M$9
Name MostPurchasedC: ProductsnPayements!$L$9
Name MostPurchasedNumberAllB: ProductsnPayements!$S$9
Name MostPurchaseFilter: 'Data Validation'!$O$15
Name MostPurchaseFilterNumber: 'Data Validation'!$O$16
Name PayementFilter: 'Data Validation'!$G$18
Name TotalCustomer: 'Data Validation'!$I$10
Name TotalCustomers: 'Data Validation'!$J$6
Name TotalRevenue: 'Data Validation'!$H$6

Sheet Data Validation
A1: Branch | B1: Gender | C1: Total
A2: A | B2: M
A3: B | B3: F
A4: C | B4: All
A5: All | H5: Branch Revenue filter | J5: Total Customer
H6: =_xlfn.IFS(InputBranch="A",BranchARevenue,InputBranch="B",BranchBRevenue,InputBranch="C",BranchCRevenue,InputBranch="All",AllBranchRevenue) -> 20753.554 | J6: =CustomerCountA+CustomerCountB+CustomerCountC -> 161
Q7: Total quantity
A8: Payement Method | E8: Customer | Q8: =BranchAQuantity+BranchBQuantity+BranchCQuantity -> 898
A9: Credit card | E9: Normal | I9: Total customer filters | M9: All branch revenue
A10: Cash | E10: Member | I10: =_xlfn.IFS(InputBranch="A",CustomerCountA,InputBranch="B",CustomerCountB,InputBranch="C",CustomerCountC,InputBranch="All",TotalCustomers) -> 62 | M10: =BranchARevenue+BranchBRevenue+BranchCRevenue -> 51790.956
A11: Ewallet | E11: All | Q11: Branch quantiy filter
A12: All | C12: All branch Average ratings | G12: Average rating Filter | Q12: =_xlfn.IFS(InputBranch="All",AllbranchQuantiy,InputBranch="A",BranchAQuantity,InputBranch="B",BranchBQuantity,InputBranch="C",BranchCQuantity) -> 374
C13: =AVERAGE(BranchAAverage,AverageBRating,AverageCRating) -> 6.8935058 | G13: =_xlfn.IFS(InputBranch="All",AllAverage,InputBranch="A",BranchAAverage,InputBranch="B",AverageBRating,InputBranch="C",AverageCRating) -> 7.1177419 | I13: Gross incme all branch | L13: Gross income Filters
I14: =SUM(GrossProfitBranchA+GrossProfitBranchB+GrossProfitBranchC) -> 2466.236 | L14: =_xlfn.IFS(InputBranch="All",GrossProfitAllBranch,InputBranch="A",GrossProfitBranchA,InputBranch="B",GrossProfitBranchB,InputBranch="C",GrossProfitBranchC) -> 988.2645 | O14: Purchased most | R14: Purchased Least
O15: =_xlfn.IFS('Project Dashboard'!F10="All",MostPurchasedAllbranch,'Project Dashboard'!F10="A",MostPurchasedA,'Project Dashboard'!F10="B",MostPurchasedB,'Project Dashboard'!F10="C",MostPurchasedC) -> Home and lifestyle | R15: =_xlfn.IFS(InputBranch="All",LeastPurchasedAllbranch,InputBranch="A",LeastPurchaseedA,InputBranch="B",LeasPurchasedB,InputBranch="C",LeastPurchasedC) -> Health and beauty
O16: =_xlfn.IFS(InputBranch="All",MostPurchasedNumberAllB,InputBranch="A",MostpruchasedNumberBA,InputBranch="B",MostPurchasedBB,InputBranch="C",MostPurchasedBC) -> 75 | R16: =_xlfn.IFS(InputBranch="All",LeastPurchasednumberALLB,InputBranch="A",LeastPurchasedBB,InputBranch="B",LeastPurchasedBB,InputBranch="C",LeastPurchasedBC) -> 32
G18: =_xlfn.IFS(InputBranch="All",MostPayementAllBranchFilter,InputBranch="A",MostPayementAFilter,InputBranch="B",MostPayementBFilter,InputBranch="C",MostPayementCfilter) -> Ewallet

Sheet ProductsnPayements
A1: For BranchA | G1: For Branch B | L1: For Branch C | Q1: For all
A2: Electronic accessories | C2: =SUMIFS( BranchA!F:F, BranchA!$C:$C, IF(Inputgender="All","*",Inputgender), BranchA!$B:$B, IF(InputCustomertyp="All","*",InputCustomertyp), BranchA!$K:$K, IF(InputPayementMethod="All","*",InputPayementMethod),BranchA!D:D,A2 ) -> 66 | G2: Electronic accessories | I2: =SUMIFS( BranchB!$F:$F, BranchB!$C:$C, IF(Inputgender="All","*",Inputgender), BranchB!$B:$B, IF(InputCustomertyp="All","*",InputCustomertyp), BranchB!$K:$K, IF(InputPayementMethod="All","*",InputPayementMethod),BranchA!D:D,G2 ) -> 38 | L2: Electronic accessories | O2: =SUMIFS( BranchC!$F:$F, BranchC!$C:$C, IF(Inputgender="All","*",Inputgender), BranchC!$B:$B, IF(InputCustomertyp="All","*",InputCustomertyp), BranchC!$K:$K, IF(InputPayementMethod="All","*",InputPayementMethod),BranchC!D:D,L2 ) -> 46 | Q2: Electronic accessories | S2: =SUM(C2,I2,O2) -> 150
A3: Sports and travel | C3: =SUMIFS( BranchA!F:F, BranchA!$C:$C, IF(Inputgender="All","*",Inputgender), BranchA!$B:$B, IF(InputCustomertyp="All","*",InputCustomertyp), BranchA!$K:$K, IF(InputPayementMethod="All","*",InputPayementMethod),BranchA!D:D,A3 ) -> 69 | G3: Sports and travel | I3: =SUMIFS( BranchB!$F:$F, BranchB!$C:$C, IF(Inputgender="All","*",Inputgender), BranchB!$B:$B, IF(InputCustomertyp="All","*",InputCustomertyp), BranchB!$K:$K, IF(InputPayementMethod="All","*",InputPayementMethod),BranchA!D:D,G3 ) -> 42 | L3: Sports and travel | O3: =SUMIFS( BranchC!$F:$F, BranchC!$C:$C, IF(Inputgender="All","*",Inputgender), BranchC!$B:$B, IF(InputCustomertyp="All","*",InputCustomertyp), BranchC!$K:$K, IF(InputPayementMethod="All","*",InputPayementMethod),BranchC!D:D,L3 ) -> 29 | Q3: Sports and travel | S3: =SUM(C3,I3,O3) -> 140
A4: Fashion accessories | C4: =SUMIFS( BranchA!F:F, BranchA!$C:$C, IF(Inputgender="All","*",Inputgender), BranchA!$B:$B, IF(InputCustomertyp="All","*",InputCustomertyp), BranchA!$K:$K, IF(InputPayementMethod="All","*",InputPayementMethod),BranchA!D:D,A4 ) -> 71 | G4: Fashion accessories | I4: =SUMIFS( BranchB!$F:$F, BranchB!$C:$C, IF(Inputgender="All","*",Inputgender), BranchB!$B:$B, IF(InputCustomertyp="All","*",InputCustomertyp), BranchB!$K:$K, IF(InputPayementMethod="All","*",InputPayementMethod),BranchA!D:D,G4 ) -> 69 | L4: Fashion accessories | O4: =SUMIFS( BranchC!$F:$F, BranchC!$C:$C, IF(Inputgender="All","*",Inputgender), BranchC!$B:$B, IF(InputCustomertyp="All","*",InputCustomertyp), BranchC!$K:$K, IF(InputPayementMethod="All","*",InputPayementMethod),BranchC!D:D,L4 ) -> 58 | Q4: Fashion accessories | S4: =SUM(C4,I4,O4) -> 198
A5: Home and lifestyle | C5: =SUMIFS( BranchA!F:F, BranchA!$C:$C, IF(Inputgender="All","*",Inputgender), BranchA!$B:$B, IF(InputCustomertyp="All","*",InputCustomertyp), BranchA!$K:$K, IF(InputPayementMethod="All","*",InputPayementMethod),BranchA!D:D,A5 ) -> 75 | G5: Home and lifestyle | I5: =SUMIFS( BranchB!$F:$F, BranchB!$C:$C, IF(Inputgender="All","*",Inputgender), BranchB!$B:$B, IF(InputCustomertyp="All","*",InputCustomertyp), BranchB!$K:$K, IF(InputPayementMethod="All","*",InputPayementMethod),BranchA!D:D,G5 ) -> 33 | L5: Home and lifestyle | O5: =SUMIFS( BranchC!$F:$F, BranchC!$C:$C, IF(Inputgender="All","*",Inputgender), BranchC!$B:$B, IF(InputCustomertyp="All","*",InputCustomertyp), BranchC!$K:$K, IF(InputPayementMethod="All","*",InputPayementMethod),BranchC!D:D,L5 ) -> 42 | Q5: Home and lifestyle | S5: =SUM(C5,I5,O5) -> 150
A6: Food and beverages | C6: =SUMIFS( BranchA!F:F, BranchA!$C:$C, IF(Inputgender="All","*",Inputgender), BranchA!$B:$B, IF(InputCustomertyp="All","*",InputCustomertyp), BranchA!$K:$K, IF(InputPayementMethod="All","*",InputPayementMethod),BranchA!D:D,A6 ) -> 51 | G6: Food and beverages | I6: =SUMIFS( BranchB!$F:$F, BranchB!$C:$C, IF(Inputgender="All","*",Inputgender), BranchB!$B:$B, IF(InputCustomertyp="All","*",InputCustomertyp), BranchB!$K:$K, IF(InputPayementMethod="All","*",InputPayementMethod),BranchA!D:D,G6 ) -> 55 | L6: Food and beverages | O6: =SUMIFS( BranchC!$F:$F, BranchC!$C:$C, IF(Inputgender="All","*",Inputgender), BranchC!$B:$B, IF(InputCustomertyp="All","*",InputCustomertyp), BranchC!$K:$K, IF(InputPayementMethod="All","*",InputPayementMethod),BranchC!D:D,L6 ) -> 56 | Q6: Food and beverages | S6: =SUM(C6,I6,O6) -> 162
A7: Health and beauty | C7: =SUMIFS( BranchA!F:F, BranchA!$C:$C, IF(Inputgender="All","*",Inputgender), BranchA!$B:$B, IF(InputCustomertyp="All","*",InputCustomertyp), BranchA!$K:$K, IF(InputPayementMethod="All","*",InputPayementMethod),BranchA!D:D,A7 ) -> 42 | G7: Health and beauty | I7: =SUMIFS( BranchB!$F:$F, BranchB!$C:$C, IF(Inputgender="All","*",Inputgender), BranchB!$B:$B, IF(InputCustomertyp="All","*",InputCustomertyp), BranchB!$K:$K, IF(InputPayementMethod="All","*",InputPayementMethod),BranchA!D:D,G7 ) -> 32 | L7: Health and beauty | O7: =SUMIFS( BranchC!$F:$F, BranchC!$C:$C, IF(Inputgender="All","*",Inputgender), BranchC!$B:$B, IF(InputCustomertyp="All","*",InputCustomertyp), BranchC!$K:$K, IF(InputPayementMethod="All","*",InputPayementMethod),BranchC!D:D,L7 ) -> 24 | Q7: Health and beauty | S7: =SUM(C7,I7,O7) -> 98
B9: =INDEX(A2:A7,MATCH(C9,C2:C7,0)) -> Home and lifestyle | C9: =MAX(C2:C7) -> 75 | G9: =INDEX(G2:G7,MATCH(H9,I2:I7,0)) -> Fashion accessories | H9: =MAX(I2:I7) -> 69 | L9: =INDEX(L2:L7,MATCH(M9,O2:O7,0)) -> Fashion accessories | M9: =MAX(O2:O7) -> 58 | R9: =INDEX(Q2:Q7,MATCH(S9,S2:S7,0)) -> Fashion accessories | S9: =MAX(S2:S7) -> 198
B10: =INDEX(A2:A7,MATCH(C10,C2:C7,0)) -> Health and beauty | C10: =MIN(C2:C7) -> 42 | G10: =INDEX(G2:G7,MATCH(H10,I2:I7,0)) -> Health and beauty | H10: =MIN(I2:I7) -> 32 | L10: =INDEX(L2:L7,MATCH(M10,O2:O7,0)) -> Health and beauty | M10: =MIN(O2:O7) -> 24 | R10: =INDEX(Q2:Q7,MATCH(S10,S2:S7,0)) -> Health and beauty | S10: =MIN(S2:S7) -> 98
A13: For BranchA | G13: For BranchB | L13: For Branch C | P13: All
A14: Ewallet | B14: =COUNTIFS( BranchA!$K:$K,ProductsnPayements!A14, BranchA!$C:$C, IF(Inputgender="All","*",Inputgender),BranchA!$B:$B, IF(InputCustomertyp="All","*",InputCustomertyp)) -> 62 | G14: Ewallet | H14: =COUNTIFS( BranchB!$K:$K,ProductsnPayements!G14, BranchB!$C:$C, IF(Inputgender="All","*",Inputgender),BranchB!$B:$B, IF(InputCustomertyp="All","*",InputCustomertyp)) -> 49 | L14: Ewallet | M14: =COUNTIFS( BranchC!$K:$K,ProductsnPayements!L14, BranchC!$C:$C, IF(Inputgender="All","*",Inputgender),BranchC!$B:$B, IF(InputCustomertyp="All","*",InputCustomertyp)) -> 50 | P14: Ewallet | Q14: =B14+H14+M14 -> 161
A15: Credit card | B15: =COUNTIFS( BranchA!$K:$K,ProductsnPayements!A15, BranchA!$C:$C, IF(Inputgender="All","*",Inputgender),BranchA!$B:$B, IF(InputCustomertyp="All","*",InputCustomertyp)) -> 49 | G15: Credit card | H15: =COUNTIFS( BranchB!$K:$K,ProductsnPayements!G15, BranchB!$C:$C, IF(Inputgender="All","*",Inputgender),BranchB!$B:$B, IF(InputCustomertyp="All","*",InputCustomertyp)) -> 63 | L15: Credit card | M15: =COUNTIFS( BranchC!$K:$K,ProductsnPayements!L15, BranchC!$C:$C, IF(Inputgender="All","*",Inputgender),BranchC!$B:$B, IF(InputCustomertyp="All","*",InputCustomertyp)) -> 60 | P15: Credit card | Q15: =B15+H15+M15 -> 172
A16: Cash | B16: =COUNTIFS( BranchA!$K:$K,ProductsnPayements!A16, BranchA!$C:$C, IF(Inputgender="All","*",Inputgender),BranchA!$B:$B, IF(InputCustomertyp="All","*",InputCustomertyp)) -> 56 | G16: Cash | H16: =COUNTIFS( BranchB!$K:$K,ProductsnPayements!G16, BranchB!$C:$C, IF(Inputgender="All","*",Inputgender),BranchB!$B:$B, IF(InputCustomertyp="All","*",InputCustomertyp)) -> 53 | L16: Cash | M16: =COUNTIFS( BranchC!$K:$K,ProductsnPayements!L16, BranchC!$C:$C, IF(Inputgender="All","*",Inputgender),BranchC!$B:$B, IF(InputCustomertyp="All","*",InputCustomertyp)) -> 59 | P16: Cash | Q16: =B16+H16+M16 -> 168
A18: Most Used | G18: Most Used | L18: Most Used | P18: Most used
A19: =INDEX(A14:A16,MATCH(B19,B14:B16,0)) -> Ewallet | B19: =MAX(B14:B16) -> 62 | G19: =INDEX(G14:G16,MATCH(H19,H14:H16,0)) -> Credit card | H19: =MAX(H14:H16) -> 63 | L19: =INDEX(L14:L16,MATCH(M19,M14:M16,0)) -> Credit card | M19: =MAX(M14:M16) -> 60 | P19: =INDEX(P14:P16,MATCH(Q19,Q14:Q16,0)) -> Credit card | Q19: =MAX(Q14:Q16) -> 172

Sheet BranchA
A1: Invoice ID | B1: Customer type | C1: Gender | D1: Product line | E1: Unit price | F1: Quantity | G1: Tax 5% | H1: Total | I1: Date | J1: Time | K1: Payment | L1: cogs | M1: gross income | N1: Rating
A2: 182-52-7000 | B2: Member | C2: F | D2: Sports and travel | E2: 27.04 | F2: 4 | G2: 5.408 | H2: 113.568 | I2: 43466 | J2: 0.85138889 | K2: Ewallet | L2: 108.16 | M2: 5.408 | N2: 6.9
A3: 765-26-6951 | B3: Normal | C3: M | D3: Sports and travel | E3: 72.61 | F3: 6 | G3: 21.783 | H3: 457.443 | I3: 43466 | J3: 0.44375 | K3: Credit card | L3: 435.66 | M3: 21.783 | N3: 6.9
A4: 530-90-9855 | B4: Member | C4: M | D4: Home and lifestyle | E4: 47.59 | F4: 8 | G4: 19.036 | H4: 399.756 | I4: 43466 | J4: 0.61597222 | K4: Cash | L4: 380.72 | M4: 19.036 | N4: 5.7
A5: 416-17-9926 | B5: Member | C5: F | D5: Electronic accessories | E5: 74.22 | F5: 10 | G5: 37.11 | H5: 779.31 | I5: 43466 | J5: 0.6125 | K5: Credit card | L5: 742.2 | M5: 37.11 | N5: 4.3
A6: 651-88-7328 | B6: Normal | C6: F | D6: Fashion accessories | E6: 65.74 | F6: 9 | G6: 29.583 | H6: 621.243 | I6: 43466 | J6: 0.57986111 | K6: Cash | L6: 591.66 | M6: 29.583 | N6: 7.7
A7: 504-35-8843 | B7: Normal | C7: M | D7: Sports and travel | E7: 42.47 | F7: 1 | G7: 2.1235 | H7: 44.5935 | I7: 43467 | J7: 0.70625 | K7: Cash | L7: 42.47 | M7: 2.1235 | N7: 5.7
A8: 712-39-0363 | B8: Member | C8: M | D8: Food and beverages | E8: 41.66 | F8: 6 | G8: 12.498 | H8: 262.458 | I8: 43467 | J8: 0.64166667 | K8: Ewallet | L8: 249.96 | M8: 12.498 | N8: 5.6
A9: 749-24-1565 | B9: Normal | C9: F | D9: Health and beauty | E9: 23.03 | F9: 9 | G9: 10.3635 | H9: 217.6335 | I9: 43468 | J9: 0.50138889 | K9: Ewallet | L9: 207.27 | M9: 10.3635 | N9: 7.9
A10: 249-42-3782 | B10: Normal | C10: M | D10: Health and beauty | E10: 70.01 | F10: 5 | G10: 17.5025 | H10: 367.5525 | I10: 43468 | J10: 0.48333333 | K10: Ewallet | L10: 350.05 | M10: 17.5025 | N10: 5.5
A11: 422-29-8786 | B11: Normal | C11: F | D11: Home and lifestyle | E11: 67.09 | F11: 5 | G11: 16.7725 | H11: 352.2225 | I11: 43468 | J11: 0.69930556 | K11: Credit card | L11: 335.45 | M11: 16.7725 | N11: 9.1
A12: 132-23-6451 | B12: Member | C12: M | D12: Health and beauty | E12: 20.97 | F12: 5 | G12: 5.2425 | H12: 110.0925 | I12: 43469 | J12: 0.55625 | K12: Cash | L12: 104.85 | M12: 5.2425 | N12: 7.8
A13: 731-14-2199 | B13: Member | C13: F | D13: Home and lifestyle | E13: 35.54 | F13: 10 | G13: 17.77 | H13: 373.17 | I13: 43469 | J13: 0.56527778 | K13: Ewallet | L13: 355.4 | M13: 17.77 | N13: 7
... A341: 676-39-6028 | B341: Member | C341: F | D341: Electronic accessories | E341: 64.44 | F341: 5 | G341: 16.11 | H341: 338.31 | I341: 43554 | J341: 0.71111111 | K341: Cash | L341: 322.2 | M341: 16.11 | N341: 6.6

Sheet BranchA info
A6: Average rating
A7: =AVERAGE(BranchA_Yangon_City[Rating]) -> 7.0270588
Q10: Customer Count
Q11: =COUNTIFS( BranchA!$C:$C, IF(Inputgender="All","*",Inputgender), BranchA!$B:$B, IF(InputCustomertyp="All","*",InputCustomertyp), BranchA!$K:$K, IF(InputPayementMethod="All","*",InputPayementMethod) ) -> 62
L12: Revenue filter
L13: =SUMIFS(BranchA!H:H, BranchA!$C:$C, IF(Inputgender="All","*",Inputgender), BranchA!$B:$B, IF(InputCustomertyp="All","*",InputCustomertyp), BranchA!$K:$K, IF(InputPayementMethod="All","*",InputPayementMethod) ) -> 20753.554 | O13: Total Quantity sold
A14: Gross Profit Fiter | C14: Average rating | O14: =SUMIFS(BranchA!F:F, BranchA!$C:$C, IF(Inputgender="All","*",Inputgender), BranchA!$B:$B, IF(InputCustomertyp="All","*",InputCustomertyp), BranchA!$K:$K, IF(InputPayementMethod="All","*",InputPayementMethod) ) -> 374
A15: =SUMIFS( BranchA!M:M, BranchA!$C:$C, IF(Inputgender="All","*",Inputgender), BranchA!$B:$B, IF(InputCustomertyp="All","*",InputCustomertyp), BranchA!$K:$K, IF(InputPayementMethod="All","*",InputPayementMethod) ) -> 988.2645 | C15: =AVERAGEIFS( BranchA!N:N, BranchA!$C:$C, IF(Inputgender="All","*",Inputgender), BranchA!$B:$B, IF(InputCustomertyp="All","*",InputCustomertyp), BranchA!$K:$K, IF(InputPayementMethod="All","*",InputPayementMethod) ) -> 7.1177419

Sheet BranchB
A1: Invoice ID | B1: Customer type | C1: Gender | D1: Product line | E1: Unit price | F1: Quantity | G1: Tax 5% | H1: Total | I1: Date | J1: Time | K1: Payment | L1: cogs | M1: gross income | N1: Rating
A2: 891-01-7034 | B2: Normal | C2: F | D2: Electronic accessories | E2: 74.71 | F2: 6 | G2: 22.413 | H2: 470.673 | I2: 43466 | J2: 0.79652778 | K2: Cash | L2: 448.26 | M2: 22.413 | N2: 6.7
A3: 746-04-1077 | B3: Member | C3: F | D3: Food and beverages | E3: 84.63 | F3: 10 | G3: 42.315 | H3: 888.615 | I3: 43466 | J3: 0.48333333 | K3: Credit card | L3: 846.3 | M3: 42.315 | N3: 9
A4: 770-42-8960 | B4: Normal | C4: M | D4: Food and beverages | E4: 21.12 | F4: 8 | G4: 8.448 | H4: 177.408 | I4: 43466 | J4: 0.81319444 | K4: Cash | L4: 168.96 | M4: 8.448 | N4: 6.3
A5: 198-84-7132 | B5: Member | C5: M | D5: Fashion accessories | E5: 40.61 | F5: 9 | G5: 18.2745 | H5: 383.7645 | I5: 43467 | J5: 0.56944444 | K5: Cash | L5: 365.49 | M5: 18.2745 | N5: 7
A6: 670-71-7306 | B6: Normal | C6: M | D6: Sports and travel | E6: 44.63 | F6: 6 | G6: 13.389 | H6: 281.169 | I6: 43467 | J6: 0.83888889 | K6: Credit card | L6: 267.78 | M6: 13.389 | N6: 5.1
A7: 244-08-0162 | B7: Normal | C7: F | D7: Health and beauty | E7: 34.21 | F7: 10 | G7: 17.105 | H7: 359.205 | I7: 43467 | J7: 0.54166667 | K7: Cash | L7: 342.1 | M7: 17.105 | N7: 5.1
A8: 744-09-5786 | B8: Normal | C8: M | D8: Electronic accessories | E8: 22.01 | F8: 6 | G8: 6.603 | H8: 138.663 | I8: 43467 | J8: 0.78472222 | K8: Cash | L8: 132.06 | M8: 6.603 | N8: 7.6
A9: 875-31-8302 | B9: Normal | C9: M | D9: Sports and travel | E9: 93.38 | F9: 1 | G9: 4.669 | H9: 98.049 | I9: 43468 | J9: 0.54652778 | K9: Cash | L9: 93.38 | M9: 4.669 | N9: 9.6
A10: 552-44-5977 | B10: Member | C10: M | D10: Health and beauty | E10: 62 | F10: 8 | G10: 24.8 | H10: 520.8 | I10: 43468 | J10: 0.79722222 | K10: Credit card | L10: 496 | M10: 24.8 | N10: 6.2
A11: 501-61-1753 | B11: Normal | C11: F | D11: Home and lifestyle | E11: 63.15 | F11: 6 | G11: 18.945 | H11: 397.845 | I11: 43468 | J11: 0.85 | K11: Ewallet | L11: 378.9 | M11: 18.945 | N11: 9.8
A12: 725-32-9708 | B12: Member | C12: F | D12: Fashion accessories | E12: 68.71 | F12: 4 | G12: 13.742 | H12: 288.582 | I12: 43469 | J12: 0.79236111 | K12: Cash | L12: 274.84 | M12: 13.742 | N12: 4.1
A13: 656-16-1063 | B13: Normal | C13: M | D13: Sports and travel | E13: 46.42 | F13: 3 | G13: 6.963 | H13: 146.223 | I13: 43469 | J13: 0.55833333 | K13: Credit card | L13: 139.26 | M13: 6.963 | N13: 4.4
... A333: 731-59-7531 | B333: Member | C333: M | D333: Health and beauty | E333: 72.57 | F333: 8 | G333: 29.028 | H333: 609.588 | I333: 43554 | J333: 0.74861111 | K333: Cash | L333: 580.56 | M333: 29.028 | N333: 4.6

Sheet Branch B info
A11: Customer Count | C11: Average rating | T11: Total Quantity sold
A12: =COUNTIFS( BranchB!$C:$C, IF(Inputgender="All","*",Inputgender), BranchB!$B:$B, IF(InputCustomertyp="All","*",InputCustomertyp), BranchB!$K:$K, IF(InputPayementMethod="All","*",InputPayementMethod) ) -> 49 | C12: =AVERAGEIFS( BranchB!N:N, BranchB!$C:$C, IF(Inputgender="All","*",Inputgender), BranchB!$B:$B, IF(InputCustomertyp="All","*",InputCustomertyp), BranchB!$K:$K, IF(InputPayementMethod="All","*",InputPayementMethod) ) -> 6.5387755 | T12: =SUMIFS(BranchB!F:F, BranchB!$C:$C, IF(Inputgender="All","*",Inputgender), BranchB!$B:$B, IF(InputCustomertyp="All","*",InputCustomertyp), BranchB!$K:$K, IF(InputPayementMethod="All","*",InputPayementMethod) ) -> 269
Q13: Revenue Condition
K14: Gross Proifit | Q14: =SUMIFS(BranchB!H:H, BranchB!$C:$C, IF(Inputgender="All","*",Inputgender), BranchB!$B:$B, IF(InputCustomertyp="All","*",InputCustomertyp), BranchB!$K:$K, IF(InputPayementMethod="All","*",InputPayementMethod) ) -> 14182.234
K15: =SUMIFS( BranchB!M:M, BranchB!$C:$C, IF(Inputgender="All","*",Inputgender), BranchB!$B:$B, IF(InputCustomertyp="All","*",InputCustomertyp), BranchB!$K:$K, IF(InputPayementMethod="All","*",InputPayementMethod) ) -> 675.3445

Sheet BranchC
A1: Invoice ID | B1: Customer type | C1: Gender | D1: Product line | E1: Unit price | F1: Quantity | G1: Tax 5% | H1: Total | I1: Date | J1: Time | K1: Payment | L1: cogs | M1: gross income | N1: Rating
A2: 493-65-6248 | B2: Member | C2: F | D2: Sports and travel | E2: 36.98 | F2: 10 | G2: 18.49 | H2: 388.29 | I2: 43466 | J2: 0.825 | K2: Credit card | L2: 369.8 | M2: 18.49 | N2: 7
A3: 271-77-8740 | B3: Member | C3: F | D3: Sports and travel | E3: 29.22 | F3: 6 | G3: 8.766 | H3: 184.086 | I3: 43466 | J3: 0.48611111 | K3: Ewallet | L3: 175.32 | M3: 8.766 | N3: 5
A4: 556-97-7101 | B4: Normal | C4: F | D4: Electronic accessories | E4: 63.22 | F4: 2 | G4: 6.322 | H4: 132.762 | I4: 43466 | J4: 0.66041667 | K4: Cash | L4: 126.44 | M4: 6.322 | N4: 8.5
A5: 133-14-7229 | B5: Normal | C5: M | D5: Health and beauty | E5: 62.87 | F5: 2 | G5: 6.287 | H5: 132.027 | I5: 43466 | J5: 0.48819444 | K5: Cash | L5: 125.74 | M5: 6.287 | N5: 5
A6: 345-68-9016 | B6: Member | C6: F | D6: Sports and travel | E6: 31.67 | F6: 8 | G6: 12.668 | H6: 266.028 | I6: 43467 | J6: 0.67986111 | K6: Credit card | L6: 253.36 | M6: 12.668 | N6: 5.6
A7: 446-47-6729 | B7: Normal | C7: M | D7: Fashion accessories | E7: 99.82 | F7: 2 | G7: 9.982 | H7: 209.622 | I7: 43467 | J7: 0.75625 | K7: Credit card | L7: 199.64 | M7: 9.982 | N7: 6.7
A8: 687-15-1097 | B8: Member | C8: F | D8: Health and beauty | E8: 21.12 | F8: 2 | G8: 2.112 | H8: 44.352 | I8: 43468 | J8: 0.80347222 | K8: Cash | L8: 42.24 | M8: 2.112 | N8: 9.7
A9: 343-87-0864 | B9: Member | C9: M | D9: Health and beauty | E9: 75.88 | F9: 1 | G9: 3.794 | H9: 79.674 | I9: 43468 | J9: 0.4375 | K9: Credit card | L9: 75.88 | M9: 3.794 | N9: 7.1
A10: 672-51-8681 | B10: Member | C10: F | D10: Electronic accessories | E10: 66.65 | F10: 9 | G10: 29.9925 | H10: 629.8425 | I10: 43469 | J10: 0.76319444 | K10: Credit card | L10: 599.85 | M10: 29.9925 | N10: 9.7
A11: 628-34-3388 | B11: Normal | C11: M | D11: Fashion accessories | E11: 27.38 | F11: 6 | G11: 8.214 | H11: 172.494 | I11: 43470 | J11: 0.87083333 | K11: Credit card | L11: 164.28 | M11: 8.214 | N11: 7.9
A12: 433-08-7822 | B12: Normal | C12: F | D12: Health and beauty | E12: 78.89 | F12: 7 | G12: 27.6115 | H12: 579.8415 | I12: 43470 | J12: 0.825 | K12: Ewallet | L12: 552.23 | M12: 27.6115 | N12: 7.5
A13: 573-98-8548 | B13: Member | C13: F | D13: Fashion accessories | E13: 31.9 | F13: 1 | G13: 1.595 | H13: 33.495 | I13: 43470 | J13: 0.52777778 | K13: Ewallet | L13: 31.9 | M13: 1.595 | N13: 9.1
... A329: 115-38-7388 | B329: Member | C329: F | D329: Fashion accessories | E329: 10.18 | F329: 8 | G329: 4.072 | H329: 85.512 | I329: 43554 | J329: 0.53541667 | K329: Credit card | L329: 81.44 | M329: 4.072 | N329: 9.5

Sheet BranchC info
B14: Customer Count | E14: Total Quantity sold | H14: Average rating | P14: Revenue
B15: =COUNTIFS( BranchC!$C:$C, IF(Inputgender="All","*",Inputgender), BranchC!$B:$B, IF(InputCustomertyp="All","*",InputCustomertyp), BranchC!$K:$K, IF(InputPayementMethod="All","*",InputPayementMethod) ) -> 50 | E15: =SUMIFS(BranchC!F:F, BranchC!$C:$C, IF(Inputgender="All","*",Inputgender), BranchC!$B:$B, IF(InputCustomertyp="All","*",InputCustomertyp), BranchC!$K:$K, IF(InputPayementMethod="All","*",InputPayementMethod) ) -> 255 | H15: =AVERAGEIFS( BranchC!N:N, BranchC!$C:$C, IF(Inputgender="All","*",Inputgender), BranchC!$B:$B, IF(InputCustomertyp="All","*",InputCustomertyp), BranchC!$K:$K, IF(InputPayementMethod="All","*",InputPayementMethod) ) -> 7.024 | P15: =SUMIFS(BranchC!H:H, BranchC!$C:$C, IF(Inputgender="All","*",Inputgender), BranchC!$B:$B, IF(InputCustomertyp="All","*",InputCustomertyp), BranchC!$K:$K, IF(InputPayementMethod="All","*",InputPayementMethod) ) -> 16855.167
K16: Gross income
K17: =SUMIFS( BranchC!M:M, BranchC!$C:$C, IF(Inputgender="All","*",Inputgender), BranchC!$B:$B, IF(InputCustomertyp="All","*",InputCustomertyp), BranchC!$K:$K, IF(InputPayementMethod="All","*",InputPayementMethod) ) -> 802.627

Sheet GraphData
A1: Branches | B1: Revenue
A2: A | B2: =BranchARevenue -> 20753.554 | C2: =IF(GraphData!A2=InputBranch,B2,NA()) -> 20753.554 | D2: =IF(GraphData!A2<>'Project Dashboard'!$F$10,B2,NA()) -> #N/A
A3: B | B3: =BranchBRevenue -> 14182.234 | C3: =IF(GraphData!A3=InputBranch,B3,NA()) -> #N/A | D3: =IF(GraphData!A3<>'Project Dashboard'!$F$10,B3,NA()) -> 14182.234
A4: C | B4: =BranchCRevenue -> 16855.167 | C4: =IF(GraphData!A4=InputBranch,B4,NA()) -> #N/A | D4: =IF(GraphData!A4<>'Project Dashboard'!$F$10,B4,NA()) -> 16855.167
A7: Branches | B7: GrossProfit | G7: Branches | H7: Payement Method | I7: Total Transactions
A8: A | B8: =GrossProfitBranchA -> 988.2645 | C8: =IF(A8=InputBranch,B8,NA()) -> 988.2645 | D8: =IF(A8<>InputBranch,B8,NA()) -> #N/A | G8: A | H8: =MostPayementAFilter -> Ewallet | I8: =MostPayementAno -> 62
A9: B | B9: =GrossProfitBranchB -> 675.3445 | C9: =IF(A9=InputBranch,B9,NA()) -> #N/A | D9: =IF(A9<>InputBranch,B9,NA()) -> 675.3445 | G9: B | H9: =MostPayementBFilter -> Credit card | I9: =MostPayementBNo -> 63
A10: C | B10: =GrossProfitBranchC -> 802.627 | C10: =IF(A10=InputBranch,B10,NA()) -> #N/A | D10: =IF(A10<>InputBranch,B10,NA()) -> 802.627 | G10: C | H10: =MostPayementCfilter -> Credit card | I10: =MostPayementCNO -> 60

Sheet Project Dashboard
F5: SuperMarket Financial Dashboard
F9: Branch | H9: Gender | J9: Customer type | L9: Payment Method
F10: A | H10: All | J10: Member | L10: Ewallet
A27: Total Revenue | E27: Total Customers: | H27: Most used Payment Method: | L27: Gross Profit | N27: Average rating
A28: =TotalRevenue -> 20753.554 | E28: =TotalCustomer -> 62 | H28: =MostPayementAllBranchFilter -> Credit card | L28: =GrossProfitAllBranch -> 2466.236 | N28: =AverageFilter -> 7.1177419
F33: Most Purchased Category | J33: Least Purchased Category
F36: =MostPurchasedAllbranch -> Fashion accessories | J36: =LeastPurchasedAllbranch -> Health and beauty

Sheet SuperMarket Sales Data
A1: Invoice ID | B1: Branch | C1: City | D1: Customer type | E1: Gender | F1: Product line | G1: Unit price | H1: Quantity | I1: Tax 5% | J1: Total | K1: Date | L1: Time | M1: Payment | N1: cogs | O1: gross margin percentage | P1: gross income | Q1: Rating
A2: 750-67-8428 | B2: A | C2: Yangon | D2: Member | E2: Female | F2: Health and beauty | G2: 74.69 | H2: 7 | I2: 26.1415 | J2: 548.9715 | K2: 43470 | L2: 0.54722222 | M2: Ewallet | N2: 522.83 | O2: 4.7619048 | P2: 26.1415 | Q2: 9.1
A3: 226-31-3081 | B3: C | C3: Naypyitaw | D3: Normal | E3: Female | F3: Electronic accessories | G3: 15.28 | H3: 5 | I3: 3.82 | J3: 80.22 | K3: 43532 | L3: 0.43680556 | M3: Cash | N3: 76.4 | O3: 4.7619048 | P3: 3.82 | Q3: 9.6
A4: 631-41-3108 | B4: A | C4: Yangon | D4: Normal | E4: Male | F4: Home and lifestyle | G4: 46.33 | H4: 7 | I4: 16.2155 | J4: 340.5255 | K4: 43527 | L4: 0.55763889 | M4: Credit card | N4: 324.31 | O4: 4.7619048 | P4: 16.2155 | Q4: 7.4
A5: 123-19-1176 | B5: A | C5: Yangon | D5: Member | E5: Male | F5: Health and beauty | G5: 58.22 | H5: 8 | I5: 23.288 | J5: 489.048 | K5: 43492 | L5: 0.85625 | M5: Ewallet | N5: 465.76 | O5: 4.7619048 | P5: 23.288 | Q5: 8.4
A6: 373-73-7910 | B6: A | C6: Yangon | D6: Normal | E6: Male | F6: Sports and travel | G6: 86.31 | H6: 7 | I6: 30.2085 | J6: 634.3785 | K6: 43504 | L6: 0.44236111 | M6: Ewallet | N6: 604.17 | O6: 4.7619048 | P6: 30.2085 | Q6: 5.3
A7: 699-14-3026 | B7: C | C7: Naypyitaw | D7: Normal | E7: Male | F7: Electronic accessories | G7: 85.39 | H7: 7 | I7: 29.8865 | J7: 627.6165 | K7: 43549 | L7: 0.77083333 | M7: Ewallet | N7: 597.73 | O7: 4.7619048 | P7: 29.8865 | Q7: 4.1
A8: 355-53-5943 | B8: A | C8: Yangon | D8: Member | E8: Female | F8: Electronic accessories | G8: 68.84 | H8: 6 | I8: 20.652 | J8: 433.692 | K8: 43521 | L8: 0.60833333 | M8: Ewallet | N8: 413.04 | O8: 4.7619048 | P8: 20.652 | Q8: 5.8
A9: 315-22-5665 | B9: C | C9: Naypyitaw | D9: Normal | E9: Female | F9: Home and lifestyle | G9: 73.56 | H9: 10 | I9: 36.78 | J9: 772.38 | K9: 43520 | L9: 0.48472222 | M9: Ewallet | N9: 735.6 | O9: 4.7619048 | P9: 36.78 | Q9: 8
A10: 665-32-9167 | B10: A | C10: Yangon | D10: Member | E10: Female | F10: Health and beauty | G10: 36.26 | H10: 2 | I10: 3.626 | J10: 76.146 | K10: 43475 | L10: 0.71875 | M10: Credit card | N10: 72.52 | O10: 4.7619048 | P10: 3.626 | Q10: 7.2
A11: 692-92-5582 | B11: B | C11: Mandalay | D11: Member | E11: Female | F11: Food and beverages | G11: 54.84 | H11: 3 | I11: 8.226 | J11: 172.746 | K11: 43516 | L11: 0.56041667 | M11: Credit card | N11: 164.52 | O11: 4.7619048 | P11: 8.226 | Q11: 5.9
A12: 351-62-0822 | B12: B | C12: Mandalay | D12: Member | E12: Female | F12: Fashion accessories | G12: 14.48 | H12: 4 | I12: 2.896 | J12: 60.816 | K12: 43502 | L12: 0.75486111 | M12: Ewallet | N12: 57.92 | O12: 4.7619048 | P12: 2.896 | Q12: 4.5
A13: 529-56-3974 | B13: B | C13: Mandalay | D13: Member | E13: Male | F13: Electronic accessories | G13: 25.51 | H13: 4 | I13: 5.102 | J13: 107.142 | K13: 43533 | L13: 0.71041667 | M13: Cash | N13: 102.04 | O13: 4.7619048 | P13: 5.102 | Q13: 6.8
... A1001: 849-09-3807 | B1001: A | C1001: Yangon | D1001: Member | E1001: Female | F1001: Fashion accessories | G1001: 88.34 | H1001: 7 | I1001: 30.919 | J1001: 649.299 | K1001: 43514 | L1001: 0.56111111 | M1001: Cash | N1001: 618.38 | O1001: 4.7619048 | P1001: 30.919 | Q1001: 6.6
